{
    "status": "1",
    "length": 5,
    "data": [
        {
            "id": "133",
            "img_name": "Blast Good Luck",
            "img_url": "https://raw.githubusercontent.com/mobapptechnology/mobapptechno_git/master/birthdaysongwithnamefifteeninoneapp/images/greetingcardmaker/images/good_luck_1.jpg",
            "category_id": "26",
            "selectable_img": "1",
            "is_available": "1",
            "is_type": "2"
        },
        {
            "id": "134",
            "img_name": "Goodbye Goodluck",
            "img_url": "https://raw.githubusercontent.com/mobapptechnology/mobapptechno_git/master/birthdaysongwithnamefifteeninoneapp/images/greetingcardmaker/images/good_luck_2.jpg",
            "category_id": "26",
            "selectable_img": "1",
            "is_available": "1",
            "is_type": "2"
        },
        {
            "id": "135",
            "img_name": "Happiness And Good Luck",
            "img_url": "https://raw.githubusercontent.com/mobapptechnology/mobapptechno_git/master/birthdaysongwithnamefifteeninoneapp/images/greetingcardmaker/images/good_luck_3.jpg",
            "category_id": "26",
            "selectable_img": "1",
            "is_available": "1",
            "is_type": "2"
        },
        {
            "id": "136",
            "img_name": "Happy Friday",
            "img_url": "https://raw.githubusercontent.com/mobapptechnology/mobapptechno_git/master/birthdaysongwithnamefifteeninoneapp/images/greetingcardmaker/images/good_luck_4.jpg",
            "category_id": "26",
            "selectable_img": "1",
            "is_available": "1",
            "is_type": "2"
        },
        {
            "id": "137",
            "img_name": "Minion Good Luck",
            "img_url": "https://raw.githubusercontent.com/mobapptechnology/mobapptechno_git/master/birthdaysongwithnamefifteeninoneapp/images/greetingcardmaker/images/good_luck_5.jpg",
            "category_id": "26",
            "selectable_img": "1",
            "is_available": "1",
            "is_type": "2"
        }
    ]
}